notif/__init__.py
notif/api.py
notif/constants.py
notif/channels/__init__.py
notif/channels/abstract_channel.py
notif/channels/create_group_whatsapp.py
notif/channels/customerio.py
notif/channels/email.py
notif/channels/list_group_whatsapp.py
notif/channels/project_push_notification.py
notif/channels/sms_message_sender.py
notif/channels/test_email.py
notif/channels/user_push_notification.py
notif/channels/whatsapp_custom_message_sender.py
notif/channels/whatsapp_template_message_sender.py
p1_notif-0.5.dist-info/METADATA
p1_notif-0.5.dist-info/WHEEL
p1_notif-0.5.dist-info/top_level.txt
p1_notif-0.5.dist-info/RECORD
