Metadata-Version: 2.1
Name: p1-notif
Version: 0.5
Summary: Notification SDK for Dekoruma's internal use
Home-page: https://github.com/Dekoruma/p1-notif
Author: Jauhar Arifin
Author-email: jauhararifin10@gmail.com
License: MIT
Requires-Dist: future
Requires-Dist: requests
